rejected_peps/__init__.py
rejected_peps/pep204.py
rejected_peps/pep211.py
rejected_peps/pep212.py
rejected_peps/pep259.py
rejected_peps/pep265.py
rejected_peps/pep276.py
rejected_peps/pep281.py
rejected_peps/pep294.py
rejected_peps/pep303.py
rejected_peps/pep313.py
rejected_peps/pep3140.py
rejected_peps/pep326.py
rejected_peps/pep335.py
rejected_peps/pep336.py
rejected_peps/pep349.py
rejected_peps/pep351.py
rejected_peps/pep416.py
rejected_peps/pep559.py
rejected_peps/pep754.py
rejected_peps-0.6.1.dist-info/LICENSE
rejected_peps-0.6.1.dist-info/METADATA
rejected_peps-0.6.1.dist-info/WHEEL
rejected_peps-0.6.1.dist-info/top_level.txt
rejected_peps-0.6.1.dist-info/RECORD
