Metadata-Version: 2.1
Name: rejected-peps
Version: 0.6.1
Summary: A Python package that implements some rejected, deferred or withdrawn PEPs.
Home-page: https://github.com/wyz23x2/rejected-peps/
Author: wyz23x2
Author-email: wyz23x2@163.com
License: UNKNOWN
Project-URL: Bug Tracker, https://github.com/wyz23x2/rejected-peps/issues
Project-URL: Changelog, https://github.com/wyz23x2/rejected-peps/blob/main/CHANGELOG.md
Platform: UNKNOWN
Classifier: Programming Language :: Python :: 3.6
Classifier: Programming Language :: Python :: 3.7
Classifier: Programming Language :: Python :: 3.8
Classifier: Programming Language :: Python :: 3.9
Classifier: Programming Language :: Python :: 3.10
Classifier: Programming Language :: Python :: Implementation :: CPython
Classifier: Programming Language :: Python :: Implementation :: PyPy
Classifier: Development Status :: 4 - Beta
Classifier: License :: OSI Approved :: MIT License
Classifier: Typing :: Typed
Requires-Python: >=3.6
License-File: LICENSE
